vcf2maf_lite/__init__.py
vcf2maf_lite/vcf2maf_lite.py
vcf2maf_lite-0.1.1.dist-info/METADATA
vcf2maf_lite-0.1.1.dist-info/WHEEL
vcf2maf_lite-0.1.1.dist-info/entry_points.txt
vcf2maf_lite-0.1.1.dist-info/RECORD
