Metadata-Version: 2.1
Name: vcf2maf_lite
Version: 0.1.1
Summary: VCF to MAF format converter
Home-page: https://github.com/genome-nexus/vcf2maf-lite
License: MIT
Keywords: vcf2maf,vcftomaf,vcf,maf,lite
Author: Angelica Ochoa
Maintainer: Ramya Madupuri
Requires-Python: >=3.7
Classifier: License :: OSI Approved :: MIT License
Classifier: Programming Language :: Python :: 3
Classifier: Programming Language :: Python :: 3.7
Classifier: Programming Language :: Python :: 3.8
Classifier: Programming Language :: Python :: 3.9
Classifier: Programming Language :: Python :: 3.10
Classifier: Programming Language :: Python :: 3.11
Classifier: Programming Language :: Python :: 3.12
Requires-Dist: chardet (>=5.0.0,<6.0.0)
Requires-Dist: click (==8.0.*)
Project-URL: Bug Tracker, https://github.com/genome-nexus/vcf2maf-lite/issues
Project-URL: Repository, https://github.com/genome-nexus/vcf2maf-lite
